pejmanai_data_analysis/__init__.py
pejmanai_data_analysis/app.py
pejmanai_data_analysis-0.1.2.dist-info/METADATA
pejmanai_data_analysis-0.1.2.dist-info/WHEEL
pejmanai_data_analysis-0.1.2.dist-info/top_level.txt
pejmanai_data_analysis-0.1.2.dist-info/RECORD
