Metadata-Version: 2.1
Name: pejmanai_data_analysis
Version: 0.1.2
Summary: A package for data analysis including data description, data preprocessing, data visualization, and modeling
Home-page: https://github.com/arad1367/pejmanai_data_analysis_pypi_package
Author: Pejman
Author-email: pejman.ebrahimi77@gmail.com
Project-URL: Source, https://github.com/arad1367/pejmanai_data_analysis_pypi_package
Project-URL: Buy me a coffee, https://ko-fi.com/arad1367
Classifier: Development Status :: 3 - Alpha
Classifier: Intended Audience :: Developers
Classifier: License :: OSI Approved :: MIT License
Classifier: Programming Language :: Python :: 3
Classifier: Programming Language :: Python :: 3.8
Classifier: Programming Language :: Python :: 3.9
Classifier: Programming Language :: Python :: 3.10
Classifier: Programming Language :: Python :: 3.11
Classifier: Programming Language :: Python :: 3.12
Requires-Python: >=3.8
Requires-Dist: pandas
Requires-Dist: matplotlib
Requires-Dist: seaborn
Requires-Dist: numpy
Requires-Dist: scikit-learn
Requires-Dist: tabulate
Requires-Dist: colorama
